Metadata-Version: 2.1
Name: tryingsnake
Version: 0.5.1
Summary: Exception handling, the functional way.
Home-page: https://github.com/zero323/tryingsnake
Author: Maciej Szymkiewicz
Author-email: matthew.szymkiewicz@gmail.com
License: MIT
Platform: UNKNOWN
Classifier: Programming Language :: Python :: 3
Classifier: Development Status :: 3 - Alpha
Classifier: License :: OSI Approved :: MIT License
Classifier: Typing :: Typed
